{"generatedAt":"2026-06-18T01:57:28.639Z","earnMult":0.1,"locations":["lake","river","pier","ocean"],"species":{"bluegill":{"max":4,"jackpot":false,"rarity":"common","sizeMin":10,"sizeMax":26,"weightMax":0.87,"spawn":{"lake":32}},"perch":{"max":5,"jackpot":false,"rarity":"common","sizeMin":15,"sizeMax":35,"weightMax":1.59,"spawn":{"lake":26,"river":18}},"carp":{"max":12,"jackpot":false,"rarity":"uncommon","sizeMin":35,"sizeMax":90,"weightMax":12.96,"spawn":{"lake":14}},"bass":{"max":14,"jackpot":false,"rarity":"uncommon","sizeMin":25,"sizeMax":60,"weightMax":4.89,"spawn":{"lake":13}},"pike":{"max":29,"jackpot":false,"rarity":"rare","sizeMin":45,"sizeMax":110,"weightMax":15.19,"spawn":{"lake":7}},"catfish":{"max":26,"jackpot":false,"rarity":"rare","sizeMin":40,"sizeMax":100,"weightMax":16.88,"spawn":{"lake":6,"river":10}},"koi":{"max":71,"jackpot":false,"rarity":"epic","sizeMin":30,"sizeMax":70,"weightMax":6.63,"spawn":{"lake":2}},"sunfish":{"max":4,"jackpot":false,"rarity":"common","sizeMin":8,"sizeMax":20,"weightMax":0.56,"spawn":{}},"crappie":{"max":4,"jackpot":false,"rarity":"common","sizeMin":15,"sizeMax":30,"weightMax":1.15,"spawn":{}},"pickerel":{"max":13,"jackpot":false,"rarity":"uncommon","sizeMin":30,"sizeMax":60,"weightMax":3.45,"spawn":{}},"bowfin":{"max":16,"jackpot":false,"rarity":"uncommon","sizeMin":40,"sizeMax":70,"weightMax":6.04,"spawn":{}},"bullhead":{"max":11,"jackpot":false,"rarity":"uncommon","sizeMin":20,"sizeMax":40,"weightMax":1.84,"spawn":{}},"gar":{"max":39,"jackpot":false,"rarity":"rare","sizeMin":60,"sizeMax":120,"weightMax":16.12,"spawn":{}},"muskie":{"max":55,"jackpot":false,"rarity":"rare","sizeMin":80,"sizeMax":150,"weightMax":32.41,"spawn":{}},"walleye":{"max":43,"jackpot":false,"rarity":"rare","sizeMin":40,"sizeMax":80,"weightMax":9.21,"spawn":{}},"tigermuskie":{"max":125,"jackpot":false,"rarity":"epic","sizeMin":90,"sizeMax":140,"weightMax":31.84,"spawn":{}},"laketrout":{"max":113,"jackpot":false,"rarity":"epic","sizeMin":50,"sizeMax":100,"weightMax":18.43,"spawn":{}},"trout":{"max":9,"jackpot":false,"rarity":"common","sizeMin":20,"sizeMax":50,"weightMax":3.38,"spawn":{"river":30}},"creekfish_albino":{"max":11,"jackpot":false,"rarity":"uncommon","sizeMin":9,"sizeMax":26,"weightMax":0.88,"spawn":{"river":14}},"creekfish_redtrout":{"max":8,"jackpot":false,"rarity":"common","sizeMin":9,"sizeMax":26,"weightMax":0.95,"spawn":{"river":18}},"creekfish_steelblue":{"max":9,"jackpot":false,"rarity":"common","sizeMin":9,"sizeMax":26,"weightMax":0.95,"spawn":{"river":16}},"creekfish_sunrise":{"max":14,"jackpot":false,"rarity":"uncommon","sizeMin":9,"sizeMax":26,"weightMax":0.95,"spawn":{"river":11}},"creekfish_berryplum":{"max":16,"jackpot":false,"rarity":"uncommon","sizeMin":9,"sizeMax":26,"weightMax":1.01,"spawn":{"river":12}},"creekfish_purple":{"max":28,"jackpot":false,"rarity":"rare","sizeMin":11,"sizeMax":28,"weightMax":1.09,"spawn":{"river":5}},"creekfish_cave":{"max":32,"jackpot":false,"rarity":"rare","sizeMin":11,"sizeMax":30,"weightMax":1.21,"spawn":{"river":4}},"grayling":{"max":15,"jackpot":false,"rarity":"uncommon","sizeMin":25,"sizeMax":45,"weightMax":1.87,"spawn":{"river":16}},"eel":{"max":20,"jackpot":false,"rarity":"uncommon","sizeMin":60,"sizeMax":150,"weightMax":8.44,"spawn":{"river":6,"pier":12}},"salmon":{"max":36,"jackpot":false,"rarity":"rare","sizeMin":50,"sizeMax":100,"weightMax":18.43,"spawn":{"river":9}},"goldentrout":{"max":89,"jackpot":false,"rarity":"epic","sizeMin":20,"sizeMax":40,"weightMax":1.84,"spawn":{"river":2}},"sturgeon":{"max":113,"jackpot":false,"rarity":"epic","sizeMin":80,"sizeMax":200,"weightMax":70.33,"spawn":{"river":3}},"minnow":{"max":1,"jackpot":false,"rarity":"common","sizeMin":5,"sizeMax":10,"weightMax":0.12,"spawn":{}},"dace":{"max":2,"jackpot":false,"rarity":"common","sizeMin":6,"sizeMax":12,"weightMax":0.18,"spawn":{}},"sucker":{"max":9,"jackpot":false,"rarity":"uncommon","sizeMin":25,"sizeMax":50,"weightMax":2.76,"spawn":{}},"fallfish":{"max":11,"jackpot":false,"rarity":"uncommon","sizeMin":20,"sizeMax":40,"weightMax":2.07,"spawn":{}},"smallmouth":{"max":19,"jackpot":false,"rarity":"uncommon","sizeMin":25,"sizeMax":55,"weightMax":5.04,"spawn":{}},"steelhead":{"max":49,"jackpot":false,"rarity":"rare","sizeMin":50,"sizeMax":100,"weightMax":16.12,"spawn":{}},"shad":{"max":27,"jackpot":false,"rarity":"rare","sizeMin":40,"sizeMax":60,"weightMax":4.24,"spawn":{}},"cobia":{"max":58,"jackpot":false,"rarity":"rare","sizeMin":60,"sizeMax":120,"weightMax":27.64,"spawn":{}},"paddlefish":{"max":118,"jackpot":false,"rarity":"epic","sizeMin":100,"sizeMax":180,"weightMax":62.18,"spawn":{}},"alligatorgar":{"max":194,"jackpot":false,"rarity":"epic","sizeMin":120,"sizeMax":250,"weightMax":191.57,"spawn":{}},"mackerel":{"max":9,"jackpot":false,"rarity":"common","sizeMin":25,"sizeMax":45,"weightMax":1.66,"spawn":{"pier":30,"ocean":22}},"flounder":{"max":19,"jackpot":false,"rarity":"uncommon","sizeMin":30,"sizeMax":65,"weightMax":4.97,"spawn":{"pier":20}},"seabass":{"max":33,"jackpot":false,"rarity":"rare","sizeMin":30,"sizeMax":60,"weightMax":5.76,"spawn":{"pier":9}},"snapper":{"max":42,"jackpot":false,"rarity":"rare","sizeMin":40,"sizeMax":80,"weightMax":10.36,"spawn":{"pier":7,"ocean":16}},"darttail":{"max":22,"jackpot":false,"rarity":"uncommon","sizeMin":18,"sizeMax":48,"weightMax":2.07,"spawn":{"pier":14}},"darttail_ice":{"max":24,"jackpot":false,"rarity":"uncommon","sizeMin":18,"sizeMax":48,"weightMax":2.07,"spawn":{"pier":12}},"darttail_coralshock":{"max":49,"jackpot":false,"rarity":"rare","sizeMin":20,"sizeMax":50,"weightMax":2.25,"spawn":{"pier":5}},"darttail_ember":{"max":53,"jackpot":false,"rarity":"rare","sizeMin":20,"sizeMax":50,"weightMax":2.25,"spawn":{"pier":4.5}},"darttail_toxic":{"max":57,"jackpot":false,"rarity":"rare","sizeMin":22,"sizeMax":52,"weightMax":2.28,"spawn":{"pier":3.5}},"porgy":{"max":6,"jackpot":false,"rarity":"common","sizeMin":20,"sizeMax":35,"weightMax":1.21,"spawn":{}},"weakfish":{"max":9,"jackpot":false,"rarity":"common","sizeMin":30,"sizeMax":60,"weightMax":4.61,"spawn":{}},"pompano":{"max":18,"jackpot":false,"rarity":"uncommon","sizeMin":25,"sizeMax":45,"weightMax":3.11,"spawn":{}},"sheepshead":{"max":24,"jackpot":false,"rarity":"uncommon","sizeMin":30,"sizeMax":70,"weightMax":10.61,"spawn":{}},"ladyfish":{"max":15,"jackpot":false,"rarity":"uncommon","sizeMin":30,"sizeMax":60,"weightMax":4.15,"spawn":{}},"kingfish":{"max":52,"jackpot":false,"rarity":"rare","sizeMin":60,"sizeMax":120,"weightMax":23.03,"spawn":{}},"crevalle":{"max":47,"jackpot":false,"rarity":"rare","sizeMin":40,"sizeMax":90,"weightMax":20.56,"spawn":{}},"spadefish":{"max":37,"jackpot":false,"rarity":"rare","sizeMin":30,"sizeMax":60,"weightMax":6.91,"spawn":{}},"tarpon":{"max":166,"jackpot":false,"rarity":"epic","sizeMin":100,"sizeMax":200,"weightMax":138.19,"spawn":{}},"permit":{"max":164,"jackpot":false,"rarity":"epic","sizeMin":40,"sizeMax":90,"weightMax":30.83,"spawn":{}},"mahi":{"max":131,"jackpot":false,"rarity":"epic","sizeMin":70,"sizeMax":140,"weightMax":27.64,"spawn":{"ocean":9}},"tuna":{"max":225,"jackpot":false,"rarity":"epic","sizeMin":100,"sizeMax":250,"weightMax":253.2,"spawn":{"ocean":7}},"swordfish":{"max":72,"jackpot":false,"rarity":"rare","sizeMin":200,"sizeMax":350,"weightMax":241.5,"spawn":{"ocean":2.2}},"marlin":{"max":527,"jackpot":false,"rarity":"legendary","sizeMin":180,"sizeMax":350,"weightMax":358.51,"spawn":{"ocean":1.8}},"deepfin":{"max":34,"jackpot":false,"rarity":"uncommon","sizeMin":22,"sizeMax":60,"weightMax":7.24,"spawn":{"ocean":12}},"deepfin_moss":{"max":36,"jackpot":false,"rarity":"uncommon","sizeMin":22,"sizeMax":60,"weightMax":7.54,"spawn":{"ocean":10}},"deepfin_amberleaf":{"max":75,"jackpot":false,"rarity":"rare","sizeMin":24,"sizeMax":66,"weightMax":9.11,"spawn":{"ocean":4.5}},"deepfin_plumtide":{"max":85,"jackpot":false,"rarity":"rare","sizeMin":24,"sizeMax":68,"weightMax":9.94,"spawn":{"ocean":3.5}},"deepfin_sunset":{"max":91,"jackpot":false,"rarity":"rare","sizeMin":24,"sizeMax":68,"weightMax":9.94,"spawn":{"ocean":3}},"skipjack":{"max":10,"jackpot":false,"rarity":"common","sizeMin":40,"sizeMax":80,"weightMax":11.52,"spawn":{}},"bonito":{"max":8,"jackpot":false,"rarity":"common","sizeMin":35,"sizeMax":70,"weightMax":9.21,"spawn":{}},"amberjack":{"max":21,"jackpot":false,"rarity":"uncommon","sizeMin":60,"sizeMax":150,"weightMax":50.64,"spawn":{}},"barracuda":{"max":22,"jackpot":false,"rarity":"uncommon","sizeMin":80,"sizeMax":180,"weightMax":51.39,"spawn":{}},"grouper":{"max":23,"jackpot":false,"rarity":"uncommon","sizeMin":60,"sizeMax":120,"weightMax":57.58,"spawn":{}},"wahoo":{"max":52,"jackpot":false,"rarity":"rare","sizeMin":100,"sizeMax":200,"weightMax":80.61,"spawn":{}},"sailfish":{"max":63,"jackpot":false,"rarity":"rare","sizeMin":150,"sizeMax":280,"weightMax":107.56,"spawn":{}},"yellowfin":{"max":220,"jackpot":false,"rarity":"epic","sizeMin":100,"sizeMax":200,"weightMax":207.28,"spawn":{}},"giantsquid":{"max":250,"jackpot":false,"rarity":"epic","sizeMin":300,"sizeMax":600,"weightMax":460.63,"spawn":{}},"pizzafish":{"max":43,"jackpot":false,"rarity":"rare","sizeMin":30,"sizeMax":50,"weightMax":6.69,"spawn":{}},"wififish":{"max":95,"jackpot":false,"rarity":"epic","sizeMin":25,"sizeMax":40,"weightMax":2.19,"spawn":{}},"bitcoinfish":{"max":2770,"jackpot":false,"rarity":"legendary","sizeMin":40,"sizeMax":70,"weightMax":50.31,"spawn":{}},"discofis":{"max":121,"jackpot":false,"rarity":"epic","sizeMin":35,"sizeMax":60,"weightMax":3.94,"spawn":{}},"ramenfish":{"max":19,"jackpot":false,"rarity":"uncommon","sizeMin":20,"sizeMax":35,"weightMax":0.8,"spawn":{}},"catfishcat":{"max":50,"jackpot":false,"rarity":"rare","sizeMin":40,"sizeMax":70,"weightMax":8.05,"spawn":{}},"clockfish":{"max":140,"jackpot":false,"rarity":"epic","sizeMin":45,"sizeMax":80,"weightMax":16.37,"spawn":{}},"laptopfish":{"max":436,"jackpot":false,"rarity":"legendary","sizeMin":50,"sizeMax":85,"weightMax":10.73,"spawn":{}},"rainbowfish":{"max":198,"jackpot":false,"rarity":"epic","sizeMin":30,"sizeMax":65,"weightMax":6.95,"spawn":{}},"sushifish":{"max":71,"jackpot":false,"rarity":"rare","sizeMin":15,"sizeMax":30,"weightMax":1.84,"spawn":{}},"blackholefish":{"max":8568,"jackpot":false,"rarity":"legendary","sizeMin":1,"sizeMax":5,"weightMax":4394.68,"spawn":{}},"cloudfish":{"max":166,"jackpot":false,"rarity":"epic","sizeMin":60,"sizeMax":120,"weightMax":0.02,"spawn":{}},"toasterfish":{"max":50,"jackpot":false,"rarity":"rare","sizeMin":25,"sizeMax":40,"weightMax":5.48,"spawn":{}},"moonfish":{"max":27699,"jackpot":false,"rarity":"legendary","sizeMin":200,"sizeMax":350,"weightMax":147871.31,"spawn":{}},"memefish":{"max":410,"jackpot":false,"rarity":"epic","sizeMin":35,"sizeMax":70,"weightMax":9.67,"spawn":{}},"smokingchicken":{"max":400000,"jackpot":true,"rarity":"legendary","sizeMin":55,"sizeMax":95,"weightMax":8.34,"spawn":{"ocean":0.05}}}}